Workbook

Sheet usurtot
A1: Date | B1: usurtot index
A2: {=_xll.BDH(B1,"px_last","2000-01-01","")} -> 36556 | B2: 4
A3: 36585 | B3: 4.1
A4: 36616 | B4: 4
A5: 36646 | B5: 3.8
A6: 36677 | B6: 4
A7: 36707 | B7: 4
A8: 36738 | B8: 4
A9: 36769 | B9: 4.1
A10: 36799 | B10: 3.9
A11: 36830 | B11: 3.9
A12: 36860 | B12: 3.9
A13: 36891 | B13: 3.9
A14: 36922 | B14: 4.2
... A315: 46112 | B315: 4.3

Sheet nfp tch
A1: Date | B1: nfp tch index
A2: {=_xll.BDH(B1,"px_last","2022-01-01","")} -> 44592 | B2: 190
A3: 44620 | B3: 819
A4: 44651 | B4: 490
A5: 44681 | B5: 308
A6: 44712 | B6: 301
A7: 44742 | B7: 434
A8: 44773 | B8: 714
A9: 44804 | B9: 290
A10: 44834 | B10: 220
A11: 44865 | B11: 357
A12: 44895 | B12: 303
A13: 44926 | B13: 100
A14: 44957 | B14: 434
... A52: 46112 | B52: 178

Sheet usjllvr%
A1: Date | B1: usjllvr% index | C1: userlayo index
A2: {=_xll.BDH(B1,"px_last","2000-01-01","")} -> 36556 | B2: 13.4 | C2: {=_xll.BDH(C1,"px_last","2000-01-01","","dts=h")} -> 31.1
A3: 36585 | B3: 13.1 | C3: 30.6
A4: 36616 | B4: 14.2 | C4: 29.8
A5: 36646 | B5: 15.2 | C5: 29.9
A6: 36677 | B6: 13.6 | C6: 28.2
A7: 36707 | B7: 12.3 | C7: 24.8
A8: 36738 | B8: 14.3 | C8: 26.8
A9: 36769 | B9: 13.3 | C9: 29.2
A10: 36799 | B10: 14.2 | C10: 31.4
A11: 36830 | B11: 14.7 | C11: 30.3
A12: 36860 | B12: 13.8 | C12: 29.5
A13: 36891 | B13: 12.5 | C13: 29.7
A14: 36922 | B14: 13.6 | C14: 28
... A315: 46112 | B315: 12.4 | C315: 35.6

Sheet napmempl
A1: Date | B1: napmempl index
A2: {=_xll.BDH(B1,"px_last","2000-01-01","")} -> 36556 | B2: 52.8
A3: 36585 | B3: 53.6
A4: 36616 | B4: 51.2
A5: 36646 | B5: 53.2
A6: 36677 | B6: 53
A7: 36707 | B7: 50.7
A8: 36738 | B8: 52.5
A9: 36769 | B9: 48.8
A10: 36799 | B10: 50.6
A11: 36830 | B11: 48.2
A12: 36860 | B12: 47.1
A13: 36891 | B13: 42.7
A14: 36922 | B14: 42.3
... A316: 46112 | B316: 48.7

Sheet napmpmi
A1: Date | B1: napmpmi index
A2: {=_xll.BDH(B1,"px_last","2000-01-01","")} -> 36556 | B2: 56.7
A3: 36585 | B3: 55.8
A4: 36616 | B4: 54.9
A5: 36646 | B5: 54.7
A6: 36677 | B6: 53.2
A7: 36707 | B7: 51.4
A8: 36738 | B8: 52.5
A9: 36769 | B9: 49.9
A10: 36799 | B10: 49.7
A11: 36830 | B11: 48.7
A12: 36860 | B12: 48.5
A13: 36891 | B13: 43.9
A14: 36922 | B14: 42.3
... A316: 46112 | B316: 52.7

Sheet napmpric
A1: Date | B1: napmpric index
A2: {=_xll.BDH(B1,"px_last","2000-01-01","")} -> 36556 | B2: 72.4
A3: 36585 | B3: 71.6
A4: 36616 | B4: 78.7
A5: 36646 | B5: 71.2
A6: 36677 | B6: 65.7
A7: 36707 | B7: 62.9
A8: 36738 | B8: 63.4
A9: 36769 | B9: 58.1
A10: 36799 | B10: 58.4
A11: 36830 | B11: 57.7
A12: 36860 | B12: 58.1
A13: 36891 | B13: 59.8
A14: 36922 | B14: 64.6
... A316: 46112 | B316: 78.3

Sheet concjobp
A1: Date | B1: concjobp index | C1: concjobh index | D1: diffusion index
A2: {=_xll.BDH(B1,"px_last","2000-01-01","")} -> 36556 | B2: 55.2 | C2: {=_xll.BDH(C1,"px_last","2000-01-01","","dts=h")} -> 11.2 | D2: =B2-C2 -> 44
A3: 36585 | B3: 51.2 | C3: 11.4 | D3: =B3-C3 -> 39.8
A4: 36616 | B4: 53.3 | C4: 10.6 | D4: =B4-C4 -> 42.7
A5: 36646 | B5: 52.4 | C5: 12.1 | D5: =B5-C5 -> 40.3
A6: 36677 | B6: 53 | C6: 11 | D6: =B6-C6 -> 42
A7: 36707 | B7: 53.7 | C7: 11.2 | D7: =B7-C7 -> 42.5
A8: 36738 | B8: 55.8 | C8: 9.6 | D8: =B8-C8 -> 46.2
A9: 36769 | B9: 53.5 | C9: 11.5 | D9: =B9-C9 -> 42
A10: 36799 | B10: 52.5 | C10: 10.6 | D10: =B10-C10 -> 41.9
A11: 36830 | B11: 50 | C11: 12 | D11: =B11-C11 -> 38
A12: 36860 | B12: 50.6 | C12: 11.1 | D12: =B12-C12 -> 39.5
A13: 36891 | B13: 50.8 | C13: 12.4 | D13: =B13-C13 -> 38.4
A14: 36922 | B14: 49 | C14: 12.8 | D14: =B14-C14 -> 36.2
... A314: 46053 | B314: 25.8 | C314: 19 | D314: =B314-C314 -> 6.8
A315: 46081 | B315: 26.7 | C315: 21
A316: 46112 | B316: 27.3 | C316: 21.5

Sheet vix
A1: Date | B1: vix index
A2: {=_xll.BDH(B1,"px_last","2025-01-01","")} -> 45659 | B2: 17.93
A3: 45660 | B3: 16.13
A4: 45663 | B4: 16.04
A5: 45664 | B5: 17.82
A6: 45665 | B6: 17.7
A7: 45666 | B7: 18.07
A8: 45667 | B8: 19.54
A9: 45670 | B9: 19.19
A10: 45671 | B10: 18.71
A11: 45672 | B11: 16.12
A12: 45673 | B12: 16.6
A13: 45674 | B13: 15.97
A14: 45677 | B14: 15.81
... A325: 46118 | B325: 24.83

Sheet goldsilver
A1: Date | B1: xau curncy | C1: xag curncy | D1: goldsilver index
A2: {=_xll.BDH(B1,"px_last","2010-01-01","","days=a","per=cm")} -> 40207 | B2: 1081.2 | C2: {=_xll.BDH(C1,"px_last","2010-01-01","","dts=h","days=a","per=cm")} -> 16.21 | D2: =B2/C2 -> 66.699568
A3: 40235 | B3: 1117.59 | C3: 16.475 | D3: =B3/C3 -> 67.835508
A4: 40268 | B4: 1113.25 | C4: 17.475 | D4: =B4/C4 -> 63.705293
A5: 40298 | B5: 1179.03 | C5: 18.64 | D5: =B5/C5 -> 63.252682
A6: 40329 | B6: 1216.3 | C6: 18.57 | D6: =B6/C6 -> 65.498115
A7: 40359 | B7: 1242.38 | C7: 18.62 | D7: =B7/C7 -> 66.722879
A8: 40389 | B8: 1181 | C8: 18.01 | D8: =B8/C8 -> 65.574681
A9: 40421 | B9: 1247.4 | C9: 19.3713 | D9: =B9/C9 -> 64.394233
A10: 40451 | B10: 1308.54 | C10: 21.7588 | D10: =B10/C10 -> 60.138427
A11: 40480 | B11: 1359.4 | C11: 24.7519 | D11: =B11/C11 -> 54.921036
A12: 40512 | B12: 1386.23 | C12: 28.0975 | D12: =B12/C12 -> 49.336418
A13: 40543 | B13: 1421.4 | C13: 30.9075 | D13: =B13/C13 -> 45.988838
A14: 40574 | B14: 1332.68 | C14: 28.065 | D14: =B14/C14 -> 47.48548
... A195: 46080 | B195: 5278.93 | C195: 93.7867 | D195: =B195/C195 -> 56.286552
A196: 46112 | B196: 4668.06 | C196: 75.169

Sheet mpmicama
A1: Date | B1: mpmicama index
A2: {=_xll.BDH(B1,"px_last","2020-01-01","")} -> 45016 | B2: 48.6
A3: 45046 | B3: 50.2
A4: 45077 | B4: 49
A5: 45107 | B5: 48.8
A6: 45138 | B6: 49.6
A7: 45169 | B7: 48
A8: 45199 | B8: 47.5
A9: 45230 | B9: 48.6
A10: 45260 | B10: 47.7
A11: 45291 | B11: 45.4
A12: 45322 | B12: 48.3
A13: 45351 | B13: 49.7
A14: 45382 | B14: 49.8
... A38: 46112 | B38: 50

Sheet iveysa
A1: Date | B1: iveysa index
A2: {=_xll.BDH(B1,"px_last","2020-01-01","")} -> 43861 | B2: 57.3
A3: 43890 | B3: 54.1
A4: 43921 | B4: 26
A5: 43951 | B5: 22.8
A6: 43982 | B6: 39.1
A7: 44012 | B7: 58.2
A8: 44043 | B8: 68.5
A9: 44074 | B9: 67.8
A10: 44104 | B10: 54.3
A11: 44135 | B11: 54.5
A12: 44165 | B12: 52.7
A13: 44196 | B13: 46.7
A14: 44227 | B14: 64.1
... A75: 46081 | B75: 56.6

Sheet trufusyy
A1: Date | B1: trufusyy index
A2: {=_xll.BDH(B1,"px_last","2020-01-01","")} -> 43831 | B2: 2.47441
A3: 43832 | B3: 2.46809
A4: 43833 | B4: 2.43182
A5: 43834 | B5: 2.43172
A6: 43835 | B6: 2.43491
A7: 43836 | B7: 2.43581
A8: 43837 | B8: 2.44101
A9: 43838 | B9: 2.42496
A10: 43839 | B10: 2.41522
A11: 43840 | B11: 2.43124
A12: 43841 | B12: 2.43161
A13: 43842 | B13: 2.42945
A14: 43843 | B14: 2.41186
... A2289: 46118 | B2289: 1.4351

Sheet canlxemr
A1: Date | B1: canlxemr index
A2: {=_xll.BDH(B1,"px_last","2000-01-01","")} -> 36556 | B2: 6.8
A3: 36585 | B3: 6.9
A4: 36616 | B4: 6.9
A5: 36646 | B5: 6.7
A6: 36677 | B6: 6.6
A7: 36707 | B7: 6.7
A8: 36738 | B8: 6.8
A9: 36769 | B9: 7
A10: 36799 | B10: 6.9
A11: 36830 | B11: 7
A12: 36860 | B12: 6.9
A13: 36891 | B13: 6.8
A14: 36922 | B14: 6.9
... A315: 46081 | B315: 6.7

Sheet camfchng
A1: Date | B1: camfchng index
A2: {=_xll.BDH(B1,"px_last","2020-01-01","")} -> 43861 | B2: -1.66
A3: 43890 | B3: 0.69
A4: 43921 | B4: -12.04
A5: 43951 | B5: -27.56
A6: 43982 | B6: 12.66
A7: 44012 | B7: 21.95
A8: 44043 | B8: 6.65
A9: 44074 | B9: -0.28
A10: 44104 | B10: 2.73
A11: 44135 | B11: 0.83
A12: 44165 | B12: -0.74
A13: 44196 | B13: 2.01
A14: 44227 | B14: 4
... A74: 46053 | B74: -3.04

Sheet adp chng
A1: Date | B1: adp chng index
A2: {=_xll.BDH(B1,"px_last","2022-01-01","")} -> 44592 | B2: 471
A3: 44620 | B3: 584
A4: 44651 | B4: 598
A5: 44681 | B5: 685
A6: 44712 | B6: 303
A7: 44742 | B7: 538
A8: 44773 | B8: 409
A9: 44804 | B9: 365
A10: 44834 | B10: 339
A11: 44865 | B11: 251
A12: 44895 | B12: 269
A13: 44926 | B13: 191
A14: 44957 | B14: 187
... A52: 46112 | B52: 62

Sheet napmnemp
A1: Date | B1: napmnemp index
A2: {=_xll.BDH(B1,"px_last","2000-01-01","")} -> 36556 | B2: 52.3
A3: 36585 | B3: 52.8
A4: 36616 | B4: 55
A5: 36646 | B5: 54.4
A6: 36677 | B6: 53.5
A7: 36707 | B7: 54.4
A8: 36738 | B8: 50.5
A9: 36769 | B9: 54.2
A10: 36799 | B10: 53.5
A11: 36830 | B11: 54.5
A12: 36860 | B12: 54.6
A13: 36891 | B13: 52.4
A14: 36922 | B14: 51.7
... A315: 46081 | B315: 51.8

Sheet napmnmi
A1: Date | B1: napmnmi index
A2: {=_xll.BDH(B1,"px_last","2000-01-01","")} -> 36556 | B2: 56.6
A3: 36585 | B3: 56.2
A4: 36616 | B4: 57.4
A5: 36646 | B5: 58
A6: 36677 | B6: 57.7
A7: 36707 | B7: 56.9
A8: 36738 | B8: 55.3
A9: 36769 | B9: 57.6
A10: 36799 | B10: 56.7
A11: 36830 | B11: 56.7
A12: 36860 | B12: 56.2
A13: 36891 | B13: 54
A14: 36922 | B14: 51.6
... A315: 46081 | B315: 56.1

Sheet napmnprc
A1: Date | B1: napmnprc index
A2: {=_xll.BDH(B1,"px_last","2000-01-01","")} -> 36556 | B2: 61.4
A3: 36585 | B3: 66.5
A4: 36616 | B4: 68.6
A5: 36646 | B5: 65
A6: 36677 | B6: 64.2
A7: 36707 | B7: 65
A8: 36738 | B8: 62.1
A9: 36769 | B9: 59.2
A10: 36799 | B10: 62.1
A11: 36830 | B11: 63.7
A12: 36860 | B12: 60.9
A13: 36891 | B13: 63.5
A14: 36922 | B14: 61.8
... A315: 46081 | B315: 63

Sheet indduois
A1: Date | B1: indduois index
A2: {=_xll.BDH(B1,"px_last","2000-01-01","")} -> 43862 | B2: 100
A3: 43863 | B3: 100.03
A4: 43864 | B4: 100.05
A5: 43865 | B5: 100.09
A6: 43866 | B6: 100.16
A7: 43867 | B7: 100.3
A8: 43868 | B8: 100.19
A9: 43869 | B9: 100.23
A10: 43870 | B10: 100.21
A11: 43871 | B11: 100.28
A12: 43872 | B12: 100.33
A13: 43873 | B13: 100.38
A14: 43874 | B14: 100.4
... A2248: 46108 | B2248: 101.44

Sheet conspxme
A1: Date | B1: conspxme index
A2: {=_xll.BDH(B1,"px_last","2020-01-01","")} -> 43861 | B2: 2.9
A3: 43890 | B3: 2.8
A4: 43921 | B4: 2.5
A5: 43951 | B5: 2.4
A6: 43982 | B6: 3.3
A7: 44012 | B7: 3.3
A8: 44043 | B8: 3.6
A9: 44074 | B9: 3.4
A10: 44104 | B10: 3.3
A11: 44135 | B11: 3
A12: 44165 | B12: 3.2
A13: 44196 | B13: 3
A14: 44227 | B14: 3.8
... A76: 46112 | B76: 6.8

Sheet consp5me
A1: Date | B1: consp5me index
A2: {=_xll.BDH(B1,"px_last","2020-01-01","")} -> 43861 | B2: 2.8
A3: 43890 | B3: 2.7
A4: 43921 | B4: 2.6
A5: 43951 | B5: 2.7
A6: 43982 | B6: 2.9
A7: 44012 | B7: 2.6
A8: 44043 | B8: 2.8
A9: 44074 | B9: 2.9
A10: 44104 | B10: 3
A11: 44135 | B11: 2.6
A12: 44165 | B12: 2.9
A13: 44196 | B13: 2.9
A14: 44227 | B14: 3
... A76: 46112 | B76: 6.7

Sheet cpi_xyoy
A1: Date | B1: cpi xyoy index
A2: {=_xll.BDH(B1,"px_last","2000-01-01","")} -> 36556 | B2: 2
A3: 36585 | B3: 2.2
A4: 36616 | B4: 2.4
A5: 36646 | B5: 2.3
A6: 36677 | B6: 2.4
A7: 36707 | B7: 2.5
A8: 36738 | B8: 2.5
A9: 36769 | B9: 2.6
A10: 36799 | B10: 2.6
A11: 36830 | B11: 2.5
A12: 36860 | B12: 2.6
A13: 36891 | B13: 2.6
A14: 36922 | B14: 2.6
... A314: 46081 | B314: 2.5

Sheet cpi_yoy
A1: Date | B1: cpi xyoy index | C1: cpi yoy index
A2: {=_xll.BDH(B1,"px_last","2020-01-01","")} -> 43861 | B2: 2.3 | C2: {=_xll.BDH(C1,"px_last",A2,"","dts=h")} -> 2.5
A3: 43890 | B3: 2.4 | C3: 2.3
A4: 43921 | B4: 2.1 | C4: 1.5
A5: 43951 | B5: 1.4 | C5: 0.3
A6: 43982 | B6: 1.2 | C6: 0.1
A7: 44012 | B7: 1.2 | C7: 0.6
A8: 44043 | B8: 1.6 | C8: 1
A9: 44074 | B9: 1.7 | C9: 1.3
A10: 44104 | B10: 1.7 | C10: 1.4
A11: 44135 | B11: 1.6 | C11: 1.2
A12: 44165 | B12: 1.6 | C12: 1.2
A13: 44196 | B13: 1.6 | C13: 1.4
A14: 44227 | B14: 1.4 | C14: 1.4
... A74: 46081 | B74: 2.5 | C74: 2.4

Sheet csxhspcm
A1: Date | B1: csxhspcm index
A2: {=_xll.BDH(B1,"px_last","2019-01-01","")} -> 43496 | B2: 0.2
A3: 43524 | B3: 0.15
A4: 43555 | B4: 0.06
A5: 43585 | B5: 0.22
A6: 43616 | B6: 0.06
A7: 43646 | B7: 0.21
A8: 43677 | B8: 0.27
A9: 43708 | B9: 0.3
A10: 43738 | B10: 0.24
A11: 43769 | B11: 0.38
A12: 43799 | B12: 0.26
A13: 43830 | B13: 0.16
A14: 43861 | B14: 0.37
... A85: 46081 | B85: 0.35

Sheet injcjc
A1: Date | B1: injcjc index | C1: injcsp index
A2: {=_xll.BDH(B1,"px_last","2022-01-01","")} -> 44568 | B2: 250 | C2: {=_xll.BDH(C1,"px_last","2022-01-01","","dts=h")} -> 1721
A3: 44575 | B3: 246 | C3: 1700
A4: 44582 | B4: 240 | C4: 1709
A5: 44589 | B5: 231 | C5: 1695
A6: 44596 | B6: 210 | C6: 1671
A7: 44603 | B7: 234 | C7: 1637
A8: 44610 | B8: 224 | C8: 1615
A9: 44617 | B9: 208 | C9: 1613
A10: 44624 | B10: 222 | C10: 1583
A11: 44631 | B11: 217 | C11: 1541
A12: 44638 | B12: 207 | C12: 1518
A13: 44645 | B13: 214 | C13: 1532
A14: 44652 | B14: 214 | C14: 1492
... A221: 46101 | B221: 211 | C221: 1841
A222: 46108 | B222: 202

Sheet joltopen
A1: Date | B1: joltopen index
A2: {=_xll.BDH(B1,"px_last","2020-01-01","")} -> 43861 | B2: 4.5
A3: 43890 | B3: 4.4
A4: 43921 | B4: 3.8
A5: 43951 | B5: 3.4
A6: 43982 | B6: 4
A7: 44012 | B7: 4.3
A8: 44043 | B8: 4.5
A9: 44074 | B9: 4.4
A10: 44104 | B10: 4.4
A11: 44135 | B11: 4.6
A12: 44165 | B12: 4.6
A13: 44196 | B13: 4.5
A14: 44227 | B14: 4.8
... A75: 46081 | B75: 4.2

Sheet jltsquis
A1: Date | B1: jltsquis index | C1: jltslays index
A2: {=_xll.BDH(B1,"px_last","2022-01-01","")} -> 44592 | B2: 4413 | C2: {=_xll.BDH(C1,"px_last","2022-01-01","","dts=h")} -> 1423
A3: 44620 | B3: 4233 | C3: 1401
A4: 44651 | B4: 4447 | C4: 1377
A5: 44681 | B5: 4499 | C5: 1312
A6: 44712 | B6: 4237 | C6: 1500
A7: 44742 | B7: 4165 | C7: 1528
A8: 44773 | B8: 4031 | C8: 1462
A9: 44804 | B9: 4258 | C9: 1606
A10: 44834 | B10: 4134 | C10: 1445
A11: 44865 | B11: 3956 | C11: 1553
A12: 44895 | B12: 4083 | C12: 1472
A13: 44926 | B13: 4125 | C13: 1535
A14: 44957 | B14: 3839 | C14: 1767
... A51: 46081 | B51: 2974 | C51: 1721

Sheet chaltotl
A1: Date | B1: chaltotl index
A2: {=_xll.BDH(B1,"px_last","2022-01-01","")} -> 44592 | B2: 19064
A3: 44620 | B3: 15245
A4: 44651 | B4: 21387
A5: 44681 | B5: 24286
A6: 44712 | B6: 20712
A7: 44742 | B7: 32517
A8: 44773 | B8: 25810
A9: 44804 | B9: 20485
A10: 44834 | B10: 29989
A11: 44865 | B11: 33843
A12: 44895 | B12: 76835
A13: 44926 | B13: 43651
A14: 44957 | B14: 102943
... A52: 46112 | B52: 60620

Sheet conspxmd
A1: Date | B1: conspxmd index | C1: consp5md index
A2: {=_xll.BDH(B1,"px_last","2022-01-01","")} -> 44592 | B2: 4.9 | C2: {=_xll.BDH(C1,"px_last","2022-01-01","","dts=h")} -> 3.1
A3: 44620 | B3: 4.9 | C3: 3
A4: 44651 | B4: 5.4 | C4: 3
A5: 44681 | B5: 5.4 | C5: 3
A6: 44712 | B6: 5.3 | C6: 3
A7: 44742 | B7: 5.3 | C7: 3.1
A8: 44773 | B8: 5.2 | C8: 2.9
A9: 44804 | B9: 4.8 | C9: 2.9
A10: 44834 | B10: 4.7 | C10: 2.7
A11: 44865 | B11: 5 | C11: 2.9
A12: 44895 | B12: 5 | C12: 3
A13: 44926 | B13: 4.3 | C13: 3
A14: 44957 | B14: 3.9 | C14: 2.9
... A52: 46112 | B52: 3.8 | C52: 3.2

Sheet canlnetj
A1: Date | B1: canlnetj index
A2: {=_xll.BDH(B1,"px_last","2022-01-01","")} -> 44592 | B2: -203.4
A3: 44620 | B3: 323.6
A4: 44651 | B4: 18.8
A5: 44681 | B5: 61.9
A6: 44712 | B6: 53.7
A7: 44742 | B7: -12.6
A8: 44773 | B8: 36.7
A9: 44804 | B9: -6.3
A10: 44834 | B10: 14.9
A11: 44865 | B11: 86.7
A12: 44895 | B12: 41
A13: 44926 | B13: 74.7
A14: 44957 | B14: 99
... A51: 46081 | B51: -83.9

Sheet sboitotl
A1: Date | B1: sboitotl index
A2: {=_xll.BDH(B1,"px_last","2020-01-01","")} -> 43861 | B2: 104.3
A3: 43890 | B3: 104.5
A4: 43921 | B4: 96.4
A5: 43951 | B5: 90.9
A6: 43982 | B6: 94.4
A7: 44012 | B7: 100.6
A8: 44043 | B8: 98.8
A9: 44074 | B9: 100.2
A10: 44104 | B10: 104
A11: 44135 | B11: 104
A12: 44165 | B12: 101.4
A13: 44196 | B13: 95.9
A14: 44227 | B14: 95
... A75: 46081 | B75: 98.8

Sheet caheperm
A1: Date | B1: caheperm index
A2: {=_xll.BDH(B1,"px_last","2020-01-01","")} -> 43861 | B2: 3.1
A3: 43890 | B3: 3.64
A4: 43921 | B4: 6.26
A5: 43951 | B5: 10.16
A6: 43982 | B6: 9.59
A7: 44012 | B7: 6.63
A8: 44043 | B8: 5.79
A9: 44074 | B9: 5.73
A10: 44104 | B10: 4.93
A11: 44135 | B11: 5.51
A12: 44165 | B12: 5.01
A13: 44196 | B13: 5.25
A14: 44227 | B14: 5.88
... A75: 46081 | B75: 4.2

Sheet econcrea
A1: Date | B1: econcrea index
A2: {=_xll.BDH(B1,"px_last","2020-08-01","")} -> 44074 | B2: 6.2
A3: 44104 | B3: 0.9
A4: 44135 | B4: -0.7
A5: 44165 | B5: -1.6
A6: 44196 | B6: 7.2
A7: 44227 | B7: 2
A8: 44255 | B8: 6.6
A9: 44286 | B9: 5.2
A10: 44316 | B10: -12.5
A11: 44347 | B11: -7.4
A12: 44377 | B12: -8.4
A13: 44408 | B13: -3.5
A14: 44439 | B14: -0.5
... A68: 46081 | B68: -1.3

Sheet bm7t
A1: Date | B1: bm7t index
A2: {=_xll.BDH(B1,"px_last","2025-08-01","")} -> 45870 | B2: 28365.52
A3: 45873 | B3: 28946.83
A4: 45874 | B4: 28776.88
A5: 45875 | B5: 29331.45
A6: 45876 | B6: 29450.11
A7: 45877 | B7: 29904.22
A8: 45880 | B8: 29898.1
A9: 45881 | B9: 30246.44
A10: 45882 | B10: 30152.63
A11: 45883 | B11: 30278.32
A12: 45884 | B12: 30179.19
A13: 45887 | B13: 30132.15
A14: 45888 | B14: 29629.31
... A178: 46118 | B178: 30259.02

Sheet sox
A1: Date | B1: sox index
A2: {=_xll.BDH(B1,"px_last","2025-08-01","")} -> 45870 | B2: 5527.608
A3: 45873 | B3: 5624.41
A4: 45874 | B4: 5561.69
A5: 45875 | B5: 5550.296
A6: 45876 | B6: 5633.701
A7: 45877 | B7: 5678.016
A8: 45880 | B8: 5670.371
A9: 45881 | B9: 5840.085
A10: 45882 | B10: 5892.607
A11: 45883 | B11: 5885.49
A12: 45884 | B12: 5752.736
A13: 45887 | B13: 5776.313
A14: 45888 | B14: 5671.509
... A171: 46118 | B171: 7927.677

Sheet returns_raw_data
B1: 46022 | C1: =TODAY()-1 -> 46117 | D1: =TODAY() -> 46118
A2: SPY us equity | B2: {=_xll.BDH($A2,"px_last",B$1,B$1,"days=a")} -> 681.92 | C2: {=_xll.BDH($A2,"px_last",C$1,C$1,"days=a")} -> 655.83 | D2: {=_xll.BDH($A2,"px_last",D$1,D$1,"days=a")} -> 657.06
A3: EZU us equity | B3: {=_xll.BDH($A3,"px_last",B$1,B$1,"days=a")} -> 64.1 | C3: {=_xll.BDH($A3,"px_last",C$1,C$1,"days=a")} -> 63.11 | D3: {=_xll.BDH($A3,"px_last",D$1,D$1,"days=a")} -> 63.235
A4: EWU us equity | B4: {=_xll.BDH($A4,"px_last",B$1,B$1,"days=a")} -> 43.98 | C4: {=_xll.BDH($A4,"px_last",C$1,C$1,"days=a")} -> 46.23 | D4: {=_xll.BDH($A4,"px_last",D$1,D$1,"days=a")} -> 46.37
A5: EWC us equity | B5: {=_xll.BDH($A5,"px_last",B$1,B$1,"days=a")} -> 53.93 | C5: {=_xll.BDH($A5,"px_last",C$1,C$1,"days=a")} -> 55.32 | D5: {=_xll.BDH($A5,"px_last",D$1,D$1,"days=a")} -> 55.42
A6: EWJ us equity | B6: {=_xll.BDH($A6,"px_last",B$1,B$1,"days=a")} -> 80.74 | C6: {=_xll.BDH($A6,"px_last",C$1,C$1,"days=a")} -> 85.29 | D6: {=_xll.BDH($A6,"px_last",D$1,D$1,"days=a")} -> 85.25
A7: EEM us equity | B7: {=_xll.BDH($A7,"px_last",B$1,B$1,"days=a")} -> 54.71 | C7: {=_xll.BDH($A7,"px_last",C$1,C$1,"days=a")} -> 56.59 | D7: {=_xll.BDH($A7,"px_last",D$1,D$1,"days=a")} -> 57.24
A9: XLC us equity | B9: {=_xll.BDH($A9,"px_last",B$1,B$1,"days=a")} -> 117.72 | C9: {=_xll.BDH($A9,"px_last",C$1,C$1,"days=a")} -> 111.7 | D9: {=_xll.BDH($A9,"px_last",D$1,D$1,"days=a")} -> 112.01
A10: XLY us equity | B10: {=_xll.BDH($A10,"px_last",B$1,B$1,"days=a")} -> 119.41 | C10: {=_xll.BDH($A10,"px_last",C$1,C$1,"days=a")} -> 108.15 | D10: {=_xll.BDH($A10,"px_last",D$1,D$1,"days=a")} -> 108.515
A11: XLP us equity | B11: {=_xll.BDH($A11,"px_last",B$1,B$1,"days=a")} -> 77.68 | C11: {=_xll.BDH($A11,"px_last",C$1,C$1,"days=a")} -> 81.89 | D11: {=_xll.BDH($A11,"px_last",D$1,D$1,"days=a")} -> 82
A12: XLE us equity | B12: {=_xll.BDH($A12,"px_last",B$1,B$1,"days=a")} -> 44.71 | C12: {=_xll.BDH($A12,"px_last",C$1,C$1,"days=a")} -> 59.25 | D12: {=_xll.BDH($A12,"px_last",D$1,D$1,"days=a")} -> 59.29
A13: XLF us equity | B13: {=_xll.BDH($A13,"px_last",B$1,B$1,"days=a")} -> 54.77 | C13: {=_xll.BDH($A13,"px_last",C$1,C$1,"days=a")} -> 49.53 | D13: {=_xll.BDH($A13,"px_last",D$1,D$1,"days=a")} -> 49.68
A14: XLV us equity | B14: {=_xll.BDH($A14,"px_last",B$1,B$1,"days=a")} -> 154.8 | C14: {=_xll.BDH($A14,"px_last",C$1,C$1,"days=a")} -> 146.81 | D14: {=_xll.BDH($A14,"px_last",D$1,D$1,"days=a")} -> 146.2
... A46: GBPUSD curncy | B46: {=_xll.BDH($A46,"px_last",B$1,B$1,"days=a")} -> 1.3475 | C46: {=_xll.BDH($A46,"px_last",C$1,C$1,"days=a")} -> 1.3202 | D46: {=_xll.BDH($A46,"px_last",D$1,D$1,"days=a")} -> 1.3254

Sheet returns_regions
A1: Region | B1: YTD
A2: US (SPY) | B2: =returns_raw_data!D2/returns_raw_data!B2-1 -> -0.036455889
A3: EU (EZU) | B3: =returns_raw_data!D3/returns_raw_data!B3-1 -> -0.01349454
A4: UK (EWU) | B4: =returns_raw_data!D4/returns_raw_data!B4-1 -> 0.054342883
A5: CAN (EWC) | B5: =returns_raw_data!D5/returns_raw_data!B5-1 -> 0.027628407
A6: Japan (EWJ) | B6: =returns_raw_data!D6/returns_raw_data!B6-1 -> 0.055858311
A7: EM (EEM) | B7: =returns_raw_data!D7/returns_raw_data!B7-1 -> 0.046243831

Sheet returns_assetclass
A1: Asset | B1: YTD
A2: Equities (SPY) | B2: =returns_raw_data!D21/returns_raw_data!B21-1 -> -0.036455889
A3: Bonds (TLT) | B3: =returns_raw_data!D22/returns_raw_data!B22-1 -> -0.0074575493
A4: Cash (BIL) | B4: =returns_raw_data!D23/returns_raw_data!B23-1 -> 0.00056686365
A5: Gold (GLD) | B5: =returns_raw_data!D24/returns_raw_data!B24-1 -> 0.081930812
A6: Silver (SLV) | B6: =returns_raw_data!D25/returns_raw_data!B25-1 -> 0.018085998
A7: Copper (CPER) | B7: =returns_raw_data!D26/returns_raw_data!B26-1 -> -0.019450801
A8: Crude oil (OILK) | B8: =returns_raw_data!D27/returns_raw_data!B27-1 -> 0.44500805
A9: BitCoin (XBT) | B9: =returns_raw_data!D28/returns_raw_data!B28-1 -> -0.20940508

Sheet returns_currency

Sheet returns_ussectors

Sheet returns_thematic

Sheet usswit1
A1: Date | B1: usswit1 curncy
A2: {=_xll.BDH(B1,"px_last","2020-08-01","")} -> 44046 | B2: 1.6424
A3: 44047 | B3: 1.63
A4: 44048 | B4: 1.706
A5: 44049 | B5: 1.687
A6: 44050 | B6: 1.63
A7: 44053 | B7: 1.635
A8: 44054 | B8: 1.641
A9: 44055 | B9: 1.862
A10: 44056 | B10: 1.8312
A11: 44057 | B11: 1.8099
A12: 44060 | B12: 1.834
A13: 44061 | B13: 1.8387
A14: 44062 | B14: 1.834
... A1446: 46118 | B1446: 3.2062

Sheet usggbe05
A1: Date | B1: usggbe05 index
A2: {=_xll.BDH(B1,"px_last","2020-08-01","")} -> 44046 | B2: 1.4651
A3: 44047 | B3: 1.4657
A4: 44048 | B4: 1.5249
A5: 44049 | B5: 1.5328
A6: 44050 | B6: 1.5097
A7: 44053 | B7: 1.492
A8: 44054 | B8: 1.5084
A9: 44055 | B9: 1.5647
A10: 44056 | B10: 1.5713
A11: 44057 | B11: 1.5438
A12: 44060 | B12: 1.5442
A13: 44061 | B13: 1.5739
A14: 44062 | B14: 1.5351
... A1480: 46118 | B1480: 2.6545

Sheet 3agsreg
A1: Date | B1: 3agsreg index
A2: {=_xll.BDH(B1,"px_last","2010-08-01","")} -> 40391 | B2: 2.735
A3: 40392 | B3: 2.726
A4: 40393 | B4: 2.747
A5: 40394 | B5: 2.765
A6: 40395 | B6: 2.779
A7: 40396 | B7: 2.776
A8: 40397 | B8: 2.776
A9: 40398 | B9: 2.774
A10: 40399 | B10: 2.781
A11: 40400 | B11: 2.78
A12: 40401 | B12: 2.776
A13: 40402 | B13: 2.77
A14: 40403 | B14: 2.761
... A5727: 46117 | B5727: 4.119

Sheet trhwcoct
A1: Date | B1: trhwcoct index
A2: {=_xll.BDH(B1,"px_last","2026-01-01","")} -> 46023 | B2: 87
A3: 46024 | B3: 82
A4: 46025 | B4: 79
A5: 46026 | B5: 80
A6: 46027 | B6: 84
A7: 46028 | B7: 82
A8: 46029 | B8: 80
A9: 46030 | B9: 83
A10: 46031 | B10: 86
A11: 46032 | B11: 90
A12: 46033 | B12: 89
A13: 46034 | B13: 93
A14: 46035 | B14: 95
... A96: 46117 | B96: 1

Sheet trhecoct
A1: Date | B1: trhecoct index
A2: {=_xll.BDH(B1,"px_last","2026-01-01","")} -> 46023 | B2: 91
A3: 46024 | B3: 85
A4: 46025 | B4: 84
A5: 46026 | B5: 90
A6: 46027 | B6: 89
A7: 46028 | B7: 95
A8: 46029 | B8: 91
A9: 46030 | B9: 88
A10: 46031 | B10: 87
A11: 46032 | B11: 83
A12: 46033 | B12: 77
A13: 46034 | B13: 81
A14: 46035 | B14: 80
... A96: 46117 | B96: 1

Sheet trhetkct
A1: Date | B1: trhetkct index
A2: {=_xll.BDH(B1,"px_last","2026-01-01","")} -> 46023 | B2: 199
A3: 46024 | B3: 188
A4: 46025 | B4: 189
A5: 46026 | B5: 194
A6: 46027 | B6: 194
A7: 46028 | B7: 202
A8: 46029 | B8: 192
A9: 46030 | B9: 193
A10: 46031 | B10: 192
A11: 46032 | B11: 185
A12: 46033 | B12: 182
A13: 46034 | B13: 183
A14: 46035 | B14: 182
... A96: 46117 | B96: 11

Sheet trhwtkct
A1: Date | B1: trhwtkct index
A2: {=_xll.BDH(B1,"px_last","2026-01-01","")} -> 46023 | B2: 200
A3: 46024 | B3: 192
A4: 46025 | B4: 181
A5: 46026 | B5: 187
A6: 46027 | B6: 183
A7: 46028 | B7: 178
A8: 46029 | B8: 174
A9: 46030 | B9: 177
A10: 46031 | B10: 190
A11: 46032 | B11: 200
A12: 46033 | B12: 201
A13: 46034 | B13: 212
A14: 46035 | B14: 216
... A96: 46117 | B96: 8

Sheet ttfg1mon
A1: Date | B1: ttfg1mon index
A2: {=_xll.BDH(B1,"px_last","2024-08-01","")} -> 45505 | B2: 37.788
A3: 45506 | B3: 37.398
A4: 45509 | B4: 36.39
A5: 45510 | B5: 37.49
A6: 45512 | B6: 40.745
A7: 45513 | B7: 41.243
A8: 45516 | B8: 41.065
A9: 45517 | B9: 40.378
A10: 45518 | B10: 39.865
A11: 45523 | B11: 40.493
A12: 45524 | B12: 38.73
A13: 45525 | B13: 37.64
A14: 45526 | B14: 37.113
... A362: 46118 | B362: 49.99

Sheet cl1
A1: Date | B1: cl1 comdty
A2: {=_xll.BDH(B1,"px_last","2024-08-01","")} -> 45505 | B2: 76.31
A3: 45506 | B3: 73.52
A4: 45509 | B4: 72.94
A5: 45510 | B5: 73.2
A6: 45511 | B6: 75.23
A7: 45512 | B7: 76.19
A8: 45513 | B8: 76.84
A9: 45516 | B9: 80.06
A10: 45517 | B10: 78.35
A11: 45518 | B11: 76.98
A12: 45519 | B12: 78.16
A13: 45520 | B13: 76.65
A14: 45523 | B14: 74.37
... A422: 46118 | B422: 112.99

Sheet co1cl1
A1: Date | B1: co1 comdty | C1: cl1 comdty | D1: co1-cl1
A2: {=_xll.BDH(B1,"px_last","2024-08-01","","days=a")} -> 45505 | B2: 79.52 | C2: {=_xll.BDH(C1,"px_last","2024-08-01","","days=a","dts=h")} -> 76.31 | D2: =B2-C2 -> 3.21
A3: 45506 | B3: 76.81 | C3: 73.52 | D3: =B3-C3 -> 3.29
A4: 45507 | B4: 76.81 | C4: 73.52 | D4: =B4-C4 -> 3.29
A5: 45508 | B5: 76.81 | C5: 73.52 | D5: =B5-C5 -> 3.29
A6: 45509 | B6: 76.3 | C6: 72.94 | D6: =B6-C6 -> 3.36
A7: 45510 | B7: 76.48 | C7: 73.2 | D7: =B7-C7 -> 3.28
A8: 45511 | B8: 78.33 | C8: 75.23 | D8: =B8-C8 -> 3.1
A9: 45512 | B9: 79.16 | C9: 76.19 | D9: =B9-C9 -> 2.97
A10: 45513 | B10: 79.66 | C10: 76.84 | D10: =B10-C10 -> 2.82
A11: 45514 | B11: 79.66 | C11: 76.84 | D11: =B11-C11 -> 2.82
A12: 45515 | B12: 79.66 | C12: 76.84 | D12: =B12-C12 -> 2.82
A13: 45516 | B13: 82.3 | C13: 80.06 | D13: =B13-C13 -> 2.24
A14: 45517 | B14: 80.69 | C14: 78.35 | D14: =B14-C14 -> 2.34
... A615: 46118 | B615: 109.25 | C615: 113 | D615: =B615-C615 -> -3.75
D616: =B616-C616 -> 0
D617: =B617-C617 -> 0
D618: =B618-C618 -> 0

Sheet gcfpnpki
A1: Date | B1: gcfpnpki index
A2: {=_xll.BDH(B1,"px_last","2024-08-01","","days=a")} -> 45505 | B2: 512.52
A3: 45506 | B3: 517.2
A4: 45507 | B4: 517.2
A5: 45508 | B5: 517.2
A6: 45509 | B6: 517.2
A7: 45510 | B7: 517.2
A8: 45511 | B8: 517.2
A9: 45512 | B9: 517.2
A10: 45513 | B10: 515.52
A11: 45514 | B11: 515.52
A12: 45515 | B12: 515.52
A13: 45516 | B13: 515.52
A14: 45517 | B14: 515.52
... A615: 46118 | B615: 984.67

Sheet rcpptdis
A1: Date | B1: rcpptdis index | C1: rcpptapp index
A2: {=_xll.BDH(B1,"px_last","2025-08-01","")} -> 45870 | B2: 51.4 | C2: {=_xll.BDH(C1,"px_last","2025-08-01","","dts=h")} -> 46.3
A3: 45871 | B3: 51.3 | C3: 46.2
A4: 45872 | B4: 51.1 | C4: 46.1
A5: 45873 | B5: 51.2 | C5: 46
A6: 45874 | B6: 51.4 | C6: 45.9
A7: 45875 | B7: 51.4 | C7: 45.8
A8: 45876 | B8: 51.4 | C8: 45.9
A9: 45877 | B9: 51.4 | C9: 45.9
A10: 45878 | B10: 51.5 | C10: 45.8
A11: 45879 | B11: 51.6 | C11: 45.7
A12: 45880 | B12: 51.5 | C12: 45.8
A13: 45881 | B13: 51.3 | C13: 45.9
A14: 45882 | B14: 51.4 | C14: 45.7
... A250: 46118 | B250: 56.8 | C250: 40.9

Sheet plymc295
A1: Date | B1: plymc295 index | C1: plymc29e index
A2: {=_xll.BDH(B1,"px_last","2025-08-01","")} -> 45870 | B2: 29 | C2: {=_xll.BDH(C1,"px_last","2025-08-01","","dts=h")} -> 71
A3: 45871 | B3: 29 | C3: 71
A4: 45872 | B4: 29 | C4: 71
A5: 45873 | B5: 29 | C5: 70
A6: 45874 | B6: 28 | C6: 71
A7: 45875 | B7: 28 | C7: 71
A8: 45876 | B8: 29 | C8: 71
A9: 45877 | B9: 29 | C9: 71
A10: 45878 | B10: 29 | C10: 71
A11: 45879 | B11: 29 | C11: 70
A12: 45880 | B12: 29 | C12: 71
A13: 45881 | B13: 29 | C13: 71
A14: 45882 | B14: 30 | C14: 70
... A250: 46118 | B250: 52 | C250: 87

Sheet fzwwwst
A1: Date | B1: fzwwwst index
A2: {=_xll.BDH(B1,"px_last","2024-08-01","","days=a")} -> 45505 | B2: 1135562
A3: 45506 | B3: 1144109
A4: 45507 | B4: 1144109
A5: 45508 | B5: 1144109
A6: 45509 | B6: 1144109
A7: 45510 | B7: 1144109
A8: 45511 | B8: 1144109
A9: 45512 | B9: 1144109
A10: 45513 | B10: 1103953
A11: 45514 | B11: 1103953
A12: 45515 | B12: 1103953
A13: 45516 | B13: 1103953
A14: 45517 | B14: 1103953
... A615: 46118 | B615: 1192311

Sheet outfgaf
A1: Date | B1: outfgaf index
A2: {=_xll.BDH(B1,"px_last","2016-08-01","")} -> 42613 | B2: 5
A3: 42643 | B3: 12.5
A4: 42674 | B4: 11
A5: 42704 | B5: 10.7
A6: 42735 | B6: 22.4
A7: 42766 | B7: 24
A8: 42794 | B8: 41.4
A9: 42825 | B9: 29.6
A10: 42855 | B10: 22
A11: 42886 | B11: 33.7
A12: 42916 | B12: 28.5
A13: 42947 | B13: 22.6
A14: 42978 | B14: 19.9
... A117: 46112 | B117: 18.1

Sheet spx_pe
A1: Date | B1: spx index
A2: {=_xll.BDH(B1,"be051","2022-08-01","","BE997=1BF")} -> 44774 | B2: 17.5679
A3: 44775 | B3: 17.4518
A4: 44776 | B4: 17.7224
A5: 44777 | B5: 17.6915
A6: 44778 | B6: 17.6721
A7: 44781 | B7: 17.6643
A8: 44782 | B8: 17.6075
A9: 44783 | B9: 17.9805
A10: 44784 | B10: 17.9708
A11: 44785 | B11: 18.278
A12: 44788 | B12: 18.3431
A13: 44789 | B13: 18.3726
A14: 44790 | B14: 18.2428
... A962: 46118 | B962: 19.5403

Sheet chpmindx
A1: Date | B1: chpmindx index
A2: {=_xll.BDH(B1,"px_last","2016-08-01","")} -> 42613 | B2: 52
A3: 42643 | B3: 54.4
A4: 42674 | B4: 51.8
A5: 42704 | B5: 56.6
A6: 42735 | B6: 52.8
A7: 42766 | B7: 51.3
A8: 42794 | B8: 56.6
A9: 42825 | B9: 58
A10: 42855 | B10: 59.9
A11: 42886 | B11: 59.1
A12: 42916 | B12: 63.5
A13: 42947 | B13: 59.7
A14: 42978 | B14: 59.3
... A117: 46112 | B117: 52.8

Sheet concconf
A1: Date | B1: concconf index
A2: {=_xll.BDH(B1,"px_last","2016-08-01","")} -> 42613 | B2: 101.8
A3: 42643 | B3: 103.5
A4: 42674 | B4: 100.8
A5: 42704 | B5: 109.4
A6: 42735 | B6: 113.3
A7: 42766 | B7: 111.6
A8: 42794 | B8: 116.1
A9: 42825 | B9: 124.9
A10: 42855 | B10: 119.4
A11: 42886 | B11: 117.6
A12: 42916 | B12: 117.3
A13: 42947 | B13: 120
A14: 42978 | B14: 120.4
... A117: 46112 | B117: 91.8

Sheet dfedgba
A1: Date | B1: dfedgba index | C1: dsergbcc index
A2: {=_xll.BDH(B1,"px_last","2016-08-01","")} -> 42613 | B2: -6.1 | C2: {=_xll.BDH(C1,"px_last","2016-08-01","","dts=h")} -> -6.7
A3: 42643 | B3: -2.6 | C3: 2.6
A4: 42674 | B4: -1.6 | C4: 2.2
A5: 42704 | B5: 12.7 | C5: 11.5
A6: 42735 | B6: 17.5 | C6: 19.3
A7: 42766 | B7: 22.1 | C7: 21.4
A8: 42794 | B8: 23.1 | C8: 13.4
A9: 42825 | B9: 17.6 | C9: 15.4
A10: 42855 | B10: 17.6 | C10: 10.4
A11: 42886 | B11: 20.1 | C11: 9.6
A12: 42916 | B12: 15.1 | C12: 10.2
A13: 42947 | B13: 16.9 | C13: 9.4
A14: 42978 | B14: 16 | C14: 14.3
... A117: 46112 | B117: -0.2 | C117: -13.3

Sheet hpimmom%
A1: Date | B1: hpimmom% index
A2: {=_xll.BDH(B1,"px_last","2016-08-01","")} -> 42613 | B2: 0.5
A3: 42643 | B3: 0.6
A4: 42674 | B4: 0.5
A5: 42704 | B5: 0.4
A6: 42735 | B6: 0.6
A7: 42766 | B7: 0.1
A8: 42794 | B8: 0.5
A9: 42825 | B9: 0.6
A10: 42855 | B10: 0.7
A11: 42886 | B11: 0.5
A12: 42916 | B12: 0.4
A13: 42947 | B13: 0.5
A14: 42978 | B14: 0.7
... A115: 46053 | B115: 0.1

Sheet spcs20y%
A1: Date | B1: spcs20y% index | C1: spcsusay index
A2: {=_xll.BDH(B1,"px_last","2016-08-01","")} -> 42613 | B2: 5.05 | C2: {=_xll.BDH(C1,"px_last","2016-08-01","","dts=h")} -> 4.99
A3: 42643 | B3: 5 | C3: 5.09
A4: 42674 | B4: 5 | C4: 5.13
A5: 42704 | B5: 5.15 | C5: 5.19
A6: 42735 | B6: 5.43 | C6: 5.31
A7: 42766 | B7: 5.71 | C7: 5.5
A8: 42794 | B8: 5.88 | C8: 5.56
A9: 42825 | B9: 5.89 | C9: 5.62
A10: 42855 | B10: 5.73 | C10: 5.63
A11: 42886 | B11: 5.73 | C11: 5.65
A12: 42916 | B12: 5.63 | C12: 5.68
A13: 42947 | B13: 5.77 | C13: 5.73
A14: 42978 | B14: 5.8 | C14: 5.82
... A115: 46053 | B115: 1.18 | C115: 0.91

Sheet cagdpmom
A1: Date | B1: cagdpmom index
A2: {=_xll.BDH(B1,"px_last","2016-08-01","")} -> 42613 | B2: 0.2
A3: 42643 | B3: 0.3
A4: 42674 | B4: -0.1
A5: 42704 | B5: 0.4
A6: 42735 | B6: 0.3
A7: 42766 | B7: 0.5
A8: 42794 | B8: 0.4
A9: 42825 | B9: 0.4
A10: 42855 | B10: 0.5
A11: 42886 | B11: 0.2
A12: 42916 | B12: 0.2
A13: 42947 | B13: -0.1
A14: 42978 | B14: -0.1
... A115: 46053 | B115: 0.1

Sheet h.iranconflict
A1: Date | B1: BY_IRAN | C1: AGAINST_IRAN
A2: 46082 | B2: 19 | C2: 7
A3: 46083 | B3: 27 | C3: 14
A4: 46084 | B4: 16 | C4: 12
A5: 46085 | B5: 11 | C5: 12
A6: 46086 | B6: 18 | C6: 11
A7: 46087 | B7: 18 | C7: 8
A8: 46088 | B8: 14 | C8: 6
A9: 46089 | B9: 8 | C9: 12
A10: 46090 | B10: 14 | C10: 7
A11: 46091 | B11: 14 | C11: 8
A12: 46092 | B12: 18 | C12: 5
A13: 46093 | B13: 15 | C13: 6
... A32: 46112 | B32: 2 | C32: 6
